{
  "name": "ReceiveVipchglevel",
  "base": "PersistedModel",
  "idInjection": false,
  "options": {
    "validateUpsert": true
  },
  "mssql": {
    "schema": "dbo",
    "table": "RECEIVE_VIPCHGLEVEL"
  },
  "properties": {
    "deptno": {
      "type": "String",
      "id": true,
      "required": true,
      "length": 10,
      "precision": null,
      "scale": null,
      "mssql": {
        "columnName": "DeptNo",
        "dataType": "varchar",
        "dataLength": 10,
        "dataPrecision": null,
        "dataScale": null,
        "nullable": "NO"
      },
      "_selectable": false
    },
    "opdate": {
      "type": "Date",
      "id": true,
      "required": true,
      "length": null,
      "precision": null,
      "scale": null,
      "mssql": {
        "columnName": "OpDate",
        "dataType": "datetime",
        "dataLength": null,
        "dataPrecision": null,
        "dataScale": null,
        "nullable": "NO"
      },
      "_selectable": false
    },
    "vipcode": {
      "type": "String",
      "id": true,
      "required": true,
      "length": 10,
      "precision": null,
      "scale": null,
      "mssql": {
        "columnName": "VipCode",
        "dataType": "varchar",
        "dataLength": 10,
        "dataPrecision": null,
        "dataScale": null,
        "nullable": "NO"
      },
      "_selectable": false
    },
    "casher": {
      "type": "String",
      "required": false,
      "length": 10,
      "precision": null,
      "scale": null,
      "mssql": {
        "columnName": "Casher",
        "dataType": "varchar",
        "dataLength": 10,
        "dataPrecision": null,
        "dataScale": null,
        "nullable": "YES"
      },
      "_selectable": true
    },
    "oldlevelcode": {
      "type": "String",
      "required": false,
      "length": 3,
      "precision": null,
      "scale": null,
      "mssql": {
        "columnName": "OldLevelCode",
        "dataType": "varchar",
        "dataLength": 3,
        "dataPrecision": null,
        "dataScale": null,
        "nullable": "YES"
      },
      "_selectable": true
    },
    "newlevelcode": {
      "type": "String",
      "required": false,
      "length": 3,
      "precision": null,
      "scale": null,
      "mssql": {
        "columnName": "NewLevelCode",
        "dataType": "varchar",
        "dataLength": 3,
        "dataPrecision": null,
        "dataScale": null,
        "nullable": "YES"
      },
      "_selectable": true
    },
    "salemoney": {
      "type": "Number",
      "required": false,
      "length": null,
      "precision": 18,
      "scale": 2,
      "mssql": {
        "columnName": "SaleMoney",
        "dataType": "decimal",
        "dataLength": null,
        "dataPrecision": 18,
        "dataScale": 2,
        "nullable": "YES"
      },
      "_selectable": true
    },
    "oldlevelround": {
      "type": "String",
      "required": false,
      "length": 4,
      "precision": null,
      "scale": null,
      "mssql": {
        "columnName": "OldLevelRound",
        "dataType": "varchar",
        "dataLength": 4,
        "dataPrecision": null,
        "dataScale": null,
        "nullable": "YES"
      },
      "_selectable": true
    },
    "newlevelround": {
      "type": "String",
      "required": false,
      "length": 4,
      "precision": null,
      "scale": null,
      "mssql": {
        "columnName": "NewLevelRound",
        "dataType": "varchar",
        "dataLength": 4,
        "dataPrecision": null,
        "dataScale": null,
        "nullable": "YES"
      },
      "_selectable": true
    },
    "flag": {
      "type": "Number",
      "required": false,
      "length": null,
      "precision": 10,
      "scale": 0,
      "mssql": {
        "columnName": "Flag",
        "dataType": "int",
        "dataLength": null,
        "dataPrecision": 10,
        "dataScale": 0,
        "nullable": "YES"
      },
      "_selectable": true
    }
  },
  "validations": [],
  "relations": {},
  "acls": [],
  "methods": {}
}
